fastex/__init__.py
fastex/main.py
fastex/template.html
fastex/view.html
fastex-0.0.2.dist-info/METADATA
fastex-0.0.2.dist-info/RECORD
fastex-0.0.2.dist-info/WHEEL
fastex-0.0.2.dist-info/entry_points.txt
fastex-0.0.2.dist-info/top_level.txt
