Metadata-Version: 2.1
Name: fastex
Version: 0.0.2
Summary: Python-based tool to quickly view data
Home-page: https://github.com/arunchaganty/fex
Author: Arun Tejasvi Chaganty
Author-email: chaganty@cs.stanford.edu
License: MIT
Keywords: html data visualization
Platform: UNKNOWN
Classifier: Development Status :: 4 - Beta
Classifier: Intended Audience :: Developers
Classifier: Intended Audience :: Science/Research
Classifier: Topic :: Scientific/Engineering :: Human Machine Interfaces
Classifier: License :: OSI Approved :: MIT License
Classifier: Programming Language :: Python :: 3
Classifier: Programming Language :: Python :: 3.5
Classifier: Programming Language :: Python :: 3.6
Provides-Extra: test
Provides-Extra: dev
Requires-Dist: bottle
Requires-Dist: Jinja2
Provides-Extra: dev
Requires-Dist: check-manifest; extra == 'dev'
Provides-Extra: test
Requires-Dist: coverage; extra == 'test'
